ruffit/__init__.py
ruffit/run.py
ruffit/utils.py
ruffit/watcher.py
ruffit-0.2.0.dist-info/licenses/LICENSE
ruffit-0.2.0.dist-info/METADATA
ruffit-0.2.0.dist-info/WHEEL
ruffit-0.2.0.dist-info/entry_points.txt
ruffit-0.2.0.dist-info/top_level.txt
ruffit-0.2.0.dist-info/RECORD
