Metadata-Version: 2.4
Name: ruffit
Version: 0.2.0
Summary: Monitor Python files and auto-run ruff, ty, and formatting checks on change. Fast, colorful, and easy CLI for code quality automation.
Author-email: Joseph Churchley <joseph.churchley@outlook.com>
License: # MIT License
Requires-Python: >=3.12
License-File: LICENSE
Requires-Dist: rich>=14.1.0
Requires-Dist: ruff>=0.12.9
Requires-Dist: ty>=0.0.1a18
Requires-Dist: typer>=0.16.1
Requires-Dist: watchdog>=6.0.0
Dynamic: license-file
